Metadata-Version: 2.1
Name: dslogparser
Version: 1.0.3
Summary: FIRST FRC Driver Station logs parser
Home-page: http://github.com/ligerbots/dslogparser
Author: Paul Rensing
Author-email: prensing@ligerbots.org
License: MIT
Keywords: FRC,logfiles
Platform: UNKNOWN
Classifier: Development Status :: 5 - Production/Stable
Classifier: Environment :: Console
Classifier: Intended Audience :: Developers
Classifier: Intended Audience :: Education
Classifier: License :: OSI Approved :: MIT License
Classifier: Programming Language :: Python :: 3
